AUTHORS
LICENSE.txt
MANIFEST.in
README.md
setup.py
dev_db/__init__.py
dev_db/creator.py
dev_db/decorators.py
dev_db/dependencies.py
dev_db/models.py
dev_db/tests.py
dev_db/utils.py
dev_db.egg-info/PKG-INFO
dev_db.egg-info/SOURCES.txt
dev_db.egg-info/dependency_links.txt
dev_db.egg-info/not-zip-safe
dev_db.egg-info/requires.txt
dev_db.egg-info/top_level.txt
dev_db/management/__init__.py
dev_db/management/commands/__init__.py
dev_db/management/commands/create_dev_db.py
dev_db/management/commands/load_dev_db.py
dev_db/management/commands/rebuild_fixtures.py