Metadata-Version: 1.0
Name: dev-db
Version: 0.2.8
Summary: Tool to automatically create a development database for local development by sampling your production database.
